docs/source/conf.py
requirements/README.md
requirements/benchmark.txt
requirements/default.txt
requirements/developer.txt
requirements/docs.txt
requirements/release.txt
requirements/test.txt
requirements/tutorial.txt
tests/algorithms/test_all.py
tools/generate_changelog.py
tools/generate_requirements.py
venv/bin/readelf.py
xgi_optimized/__init__.py
xgi_optimized/cpp_functions.cpython-313-x86_64-linux-gnu.so
xgi_optimized/optimized.py
xgi_optimized/algorithms/__init__.py
xgi_optimized/algorithms/centrality.py
xgi_optimized/algorithms/connected.py
xgi_optimized/convert/__init__.py
xgi_optimized/convert/bipartite_graph.py
xgi_optimized/convert/graph.py
xgi_optimized/convert/line_graph.py
xgi_optimized/core/__init__.py
xgi_optimized/core/simplicialcomplex.py
xgi_optimized/cpp_functions/main.cpp
xgi_optimized/cpp_functions/algorithms/centrality.cpp
xgi_optimized/cpp_functions/algorithms/centrality.h
xgi_optimized/cpp_functions/algorithms/connected.cpp
xgi_optimized/cpp_functions/algorithms/connected.h
xgi_optimized/cpp_functions/convert/line_graph.cpp
xgi_optimized/cpp_functions/convert/line_graph.h
xgi_optimized/drawing/__init__.py
xgi_optimized/drawing/layout.py
xgi_optimized/generators/__init__.py
xgi_optimized/generators/simplicial_complexes.py
xgi_optimized-0.11.1.dist-info/METADATA
xgi_optimized-0.11.1.dist-info/WHEEL
xgi_optimized-0.11.1.dist-info/top_level.txt
xgi_optimized-0.11.1.dist-info/RECORD
