Metadata-Version: 2.4
Name: xgi_optimized
Version: 0.11.1
Summary: XGI extension for faster hypergraph operations
Author: Evgeniyy2004a, TimurPshITMO, Samoylo57
Author-email: MrDragar <yshhenyaev@mail.ru>
Maintainer: Evgeniyy2004a, TimurPshITMO, Samoylo57
Maintainer-email: MrDragar <yshhenyaev@mail.ru>
License-Expression: BSD-3-Clause
Project-URL: Documentation, https://xgi.readthedocs.io/en/stable/
Project-URL: Bug Reports, https://github.com/xgi-org/xgi/issues
Project-URL: Source, https://github.com/xgi-org/xgi
Project-URL: PyPI, https://pypi.org/project/xgi/
Project-URL: GitHub Discussions, https://github.com/xgi-org/xgi/discussions
Keywords: igraph,C++,networks,higher-order,higher-order network,hypergraph,simplicial complex,network science
Classifier: Development Status :: 5 - Production/Stable
Classifier: Intended Audience :: Developers
Classifier: Intended Audience :: Science/Research
Classifier: Operating System :: OS Independent
Classifier: Programming Language :: Python :: 3
Classifier: Programming Language :: Python :: 3.10
Classifier: Programming Language :: Python :: 3.11
Classifier: Programming Language :: Python :: 3.12
Classifier: Programming Language :: Python :: 3.13
Classifier: Programming Language :: Python :: 3 :: Only
Classifier: Topic :: Software Development :: Libraries :: Python Modules
Classifier: Topic :: Scientific/Engineering :: Bio-Informatics
Classifier: Topic :: Scientific/Engineering :: Information Analysis
Classifier: Topic :: Scientific/Engineering :: Mathematics
Classifier: Topic :: Scientific/Engineering :: Physics
Requires-Python: >=3.10
Requires-Dist: numpy>=1.23.5
Requires-Dist: scipy>=1.15
Requires-Dist: pandas>=1.3
Requires-Dist: networkx>=2.7
Requires-Dist: requests>=2.0
Requires-Dist: matplotlib>=3.4
Requires-Dist: seaborn>=0.10
Requires-Dist: igraph>=0.11.8
Requires-Dist: pybind11>=2.13.6
Requires-Dist: xgi
Provides-Extra: benchmark
Requires-Dist: pytest>=7.2; extra == "benchmark"
Requires-Dist: pytest-benchmark>=5.0; extra == "benchmark"
Provides-Extra: developer
Requires-Dist: black[jupyter]>=24.3; extra == "developer"
Requires-Dist: isort==5.10.1; extra == "developer"
Requires-Dist: pylint>=3.0; extra == "developer"
Requires-Dist: nbqa; extra == "developer"
Provides-Extra: docs
Requires-Dist: sphinx~=6.0; extra == "docs"
Requires-Dist: sphinx_copybutton; extra == "docs"
Requires-Dist: sphinx-rtd-theme>=1.2; extra == "docs"
Requires-Dist: numpydoc>=1.1; extra == "docs"
Requires-Dist: pillow>=8.2; extra == "docs"
Requires-Dist: matplotlib>=3.3; extra == "docs"
Requires-Dist: sphinx-design; extra == "docs"
Requires-Dist: ipykernel; extra == "docs"
Requires-Dist: nbsphinx; extra == "docs"
Requires-Dist: nbsphinx-link; extra == "docs"
Requires-Dist: pydata-sphinx-theme; extra == "docs"
Requires-Dist: sphinx-gallery; extra == "docs"
Provides-Extra: release
Requires-Dist: twine>=3.4; extra == "release"
Requires-Dist: build>=1.2.1; extra == "release"
Requires-Dist: wheel>=0.36; extra == "release"
Provides-Extra: test
Requires-Dist: pytest>=7.2; extra == "test"
Requires-Dist: pytest-cov>=4.0; extra == "test"
Provides-Extra: tutorial
Requires-Dist: jupyter>=1.0; extra == "tutorial"
Requires-Dist: ipython<=8.12.0; extra == "tutorial"
Provides-Extra: all
Requires-Dist: xgi_optimized[benchmark,developer,docs,release,test,tutorial]; extra == "all"
